{
    "Txt_Name": "Lesson_31604",
    "Logs": [
        {
            "index": 1,
            "scenarioIndex": 19,
            "Type": 0,
            "heroineId": [
                6
            ],
            "name": {
                "default": "赤川千紗"
            },
            "message": {
                "default": "さーて……。\nこれで終わり……、っと。"
            },
            "voice": "lesson/Lesson_31604/lesson_31604_001.mp3"
        },
        {
            "index": 2,
            "scenarioIndex": 24,
            "Type": 0,
            "heroineId": [
                6
            ],
            "name": {
                "default": "赤川千紗"
            },
            "message": {
                "default": "今日はバイトもないし、\n溜まってる家事を色々片付けたいわね……。"
            },
            "voice": "lesson/Lesson_31604/lesson_31604_002.mp3"
        },
        {
            "index": 3,
            "scenarioIndex": 29,
            "Type": 0,
            "heroineId": [
                6
            ],
            "name": {
                "default": "赤川千紗"
            },
            "message": {
                "default": "……いい天気。"
            },
            "voice": "lesson/Lesson_31604/lesson_31604_003.mp3"
        },
        {
            "index": 4,
            "scenarioIndex": 33,
            "Type": 0,
            "heroineId": [
                6
            ],
            "name": {
                "default": "赤川千紗"
            },
            "message": {
                "default": "よし。今日はまずは洗濯から。"
            },
            "voice": "lesson/Lesson_31604/lesson_31604_004.mp3"
        },
        {
            "index": 5,
            "scenarioIndex": 36,
            "Type": 0,
            "heroineId": [
                6
            ],
            "name": {
                "default": "赤川千紗"
            },
            "message": {
                "default": "悠希、柚葉、あいりー！\n洗濯物あったら全部出しといてー。"
            },
            "voice": "lesson/Lesson_31604/lesson_31604_005.mp3"
        },
        {
            "index": 6,
            "scenarioIndex": 38,
            "Type": 0,
            "heroineId": [
                5,
                7,
                8
            ],
            "name": {
                "default": "3人"
            },
            "message": {
                "default": "はーい。"
            },
            "voice": "lesson/Lesson_31604/lesson_31604_006.mp3"
        },
        {
            "index": 7,
            "scenarioIndex": 41,
            "Type": 0,
            "heroineId": [
                6
            ],
            "name": {
                "default": "赤川千紗"
            },
            "message": {
                "default": "このかごに入れとくのよ？"
            },
            "voice": "lesson/Lesson_31604/lesson_31604_007.mp3"
        },
        {
            "index": 8,
            "scenarioIndex": 42,
            "Type": 0,
            "heroineId": [
                5,
                7,
                8
            ],
            "name": {
                "default": "3人"
            },
            "message": {
                "default": "はーい。"
            },
            "voice": "lesson/Lesson_31604/lesson_31604_008.mp3"
        },
        {
            "index": 9,
            "scenarioIndex": 54,
            "Type": 0,
            "heroineId": [
                6
            ],
            "name": {
                "default": "赤川千紗"
            },
            "message": {
                "default": "あらら……。\n思ったより溜まってるわね……。"
            },
            "voice": "lesson/Lesson_31604/lesson_31604_009.mp3"
        },
        {
            "index": 10,
            "scenarioIndex": 59,
            "Type": 0,
            "heroineId": [
                6
            ],
            "name": {
                "default": "赤川千紗"
            },
            "message": {
                "default": "洗濯機回したら、コーヒーでも入れようかしら。"
            },
            "voice": "lesson/Lesson_31604/lesson_31604_010.mp3"
        }
    ],
    "Language": [],
    "Translator": {}
}