{
    "Txt_Name": "HM_Cast_01_13_16_04",
    "Logs": [
        {
            "index": 1,
            "scenarioIndex": 10,
            "Type": 0,
            "heroineId": [
                0
            ],
            "name": {
                "default": "マネージャー"
            },
            "message": {
                "default": "……あれ？　利恵？"
            },
            "voice": ""
        },
        {
            "index": 2,
            "scenarioIndex": 12,
            "Type": 0,
            "heroineId": [
                13
            ],
            "name": {
                "default": "丸山利恵"
            },
            "message": {
                "default": "しーっ。鳴が起きちゃう。"
            },
            "voice": "audition/story_01/heroine_13/HM_Cast_01_13_16_04/hm_cast_01_13_16_04_002.mp3"
        },
        {
            "index": 3,
            "scenarioIndex": 14,
            "Type": 0,
            "heroineId": [
                0
            ],
            "name": {
                "default": "マネージャー"
            },
            "message": {
                "default": "あ、ごめん。\n……ぐっすり寝てるね。"
            },
            "voice": ""
        },
        {
            "index": 4,
            "scenarioIndex": 17,
            "Type": 0,
            "heroineId": [
                13
            ],
            "name": {
                "default": "丸山利恵"
            },
            "message": {
                "default": "我輩の用事が終わるまで、\n待っててくれたから。"
            },
            "voice": "audition/story_01/heroine_13/HM_Cast_01_13_16_04/hm_cast_01_13_16_04_004.mp3"
        },
        {
            "index": 5,
            "scenarioIndex": 19,
            "Type": 0,
            "heroineId": [
                13
            ],
            "name": {
                "default": "丸山利恵"
            },
            "message": {
                "default": "鳴だって忙しくて、疲れてるのに。"
            },
            "voice": "audition/story_01/heroine_13/HM_Cast_01_13_16_04/hm_cast_01_13_16_04_005.mp3"
        },
        {
            "index": 6,
            "scenarioIndex": 22,
            "Type": 0,
            "heroineId": [
                0
            ],
            "name": {
                "default": "マネージャー"
            },
            "message": {
                "default": "……そっか。\nもう帰るけど、利恵はどうする？"
            },
            "voice": ""
        },
        {
            "index": 7,
            "scenarioIndex": 24,
            "Type": 0,
            "heroineId": [
                13
            ],
            "name": {
                "default": "丸山利恵"
            },
            "message": {
                "default": "……鳴が起きるまで待ってる。\nあ、時間、大丈夫？"
            },
            "voice": "audition/story_01/heroine_13/HM_Cast_01_13_16_04/hm_cast_01_13_16_04_007.mp3"
        },
        {
            "index": 8,
            "scenarioIndex": 26,
            "Type": 0,
            "heroineId": [
                0
            ],
            "name": {
                "default": "マネージャー"
            },
            "message": {
                "default": "大丈夫。\n自分もまだ仕事するから、帰りたくなったら声かけて。"
            },
            "voice": ""
        },
        {
            "index": 9,
            "scenarioIndex": 30,
            "Type": 0,
            "heroineId": [
                13
            ],
            "name": {
                "default": "丸山利恵"
            },
            "message": {
                "default": "……うん。\nありがとう、マネージャー。"
            },
            "voice": "audition/story_01/heroine_13/HM_Cast_01_13_16_04/hm_cast_01_13_16_04_009.mp3"
        }
    ],
    "Language": [],
    "Translator": {}
}